saleae/automation/__init__.py
saleae/automation/capture.py
saleae/automation/errors.py
saleae/automation/manager.py
saleae/grpc/__init__.py
saleae/grpc/saleae_pb2.py
saleae/grpc/saleae_pb2_grpc.py
logic2_automation-1.0rc11.dist-info/METADATA
logic2_automation-1.0rc11.dist-info/WHEEL
logic2_automation-1.0rc11.dist-info/entry_points.txt
logic2_automation-1.0rc11.dist-info/RECORD
