Metadata-Version: 2.4
Name: logic2-automation
Version: 1.0rc11
Summary: Library for using the Saleae Logic 2 Automation API
Project-URL: Homepage, https://github.com/saleae/logic2-automation
Project-URL: Bug Tracker, https://github.com/saleae/logic2-automation/issues
Author-email: "Saleae, Inc." <support@saleae.com>
Classifier: Programming Language :: Python :: 3
Requires-Python: >=3.7
Requires-Dist: grpcio>=1.49.0
Requires-Dist: protobuf>=3.20.0
Requires-Dist: pywin32; platform_system == 'Windows'
